chart_studio/__init__.py
chart_studio/config.py
chart_studio/exceptions.py
chart_studio/files.py
chart_studio/session.py
chart_studio/tools.py
chart_studio/utils.py
chart_studio/api/__init__.py
chart_studio/api/utils.py
chart_studio/api/v2/__init__.py
chart_studio/api/v2/dash_apps.py
chart_studio/api/v2/dashboards.py
chart_studio/api/v2/external_files.py
chart_studio/api/v2/external_images.py
chart_studio/api/v2/files.py
chart_studio/api/v2/folders.py
chart_studio/api/v2/grids.py
chart_studio/api/v2/html_text.py
chart_studio/api/v2/images.py
chart_studio/api/v2/jupyter_notebooks.py
chart_studio/api/v2/plot_schema.py
chart_studio/api/v2/plots.py
chart_studio/api/v2/spectacle_presentations.py
chart_studio/api/v2/users.py
chart_studio/api/v2/utils.py
chart_studio/dashboard_objs/__init__.py
chart_studio/dashboard_objs/dashboard_objs.py
chart_studio/figlinq/__init__.py
chart_studio/figlinq/figlinq.py
chart_studio/grid_objs/__init__.py
chart_studio/grid_objs/grid_objs.py
chart_studio/plotly/__init__.py
chart_studio/plotly/plotly.py
chart_studio/plotly/chunked_requests/__init__.py
chart_studio/plotly/chunked_requests/chunked_request.py
chart_studio/presentation_objs/__init__.py
chart_studio/presentation_objs/presentation_objs.py
chart_studio/templates/figlinq-modern.json
chart_studio_figlinq-0.3.13.dist-info/METADATA
chart_studio_figlinq-0.3.13.dist-info/WHEEL
chart_studio_figlinq-0.3.13.dist-info/top_level.txt
chart_studio_figlinq-0.3.13.dist-info/RECORD
