Metadata-Version: 2.2
Name: chart-studio-figlinq
Version: 0.3.13
Summary: Utilities for interfacing with Plotly's Chart Studio and figlinq.com
Home-page: https://github.com/figlinq/chart-studio-figlinq
Author: figlinq.com
Author-email: info@figlinq.com
Maintainer: figlinq.com
Maintainer-email: info@figlinq.com
License: MIT
Project-URL: Github, https://github.com/figlinq/chart-studio-figlinq
Classifier: Development Status :: 5 - Production/Stable
Classifier: Programming Language :: Python :: 2
Classifier: Programming Language :: Python :: 2.7
Classifier: Programming Language :: Python :: 3
Classifier: Programming Language :: Python :: 3.5
Classifier: Programming Language :: Python :: 3.6
Classifier: Programming Language :: Python :: 3.7
Classifier: Programming Language :: Python :: 3.8
Classifier: Programming Language :: Python :: 3.9
Classifier: Programming Language :: Python :: 3.10
Classifier: Programming Language :: Python :: 3.11
Classifier: Topic :: Scientific/Engineering :: Visualization
Requires-Dist: plotly>=5.24.1
Requires-Dist: requests>=2.30.0
Requires-Dist: retrying>=1.3.3
Requires-Dist: six
Requires-Dist: cairosvg
Dynamic: author
Dynamic: author-email
Dynamic: classifier
Dynamic: description
Dynamic: description-content-type
Dynamic: home-page
Dynamic: license
Dynamic: maintainer
Dynamic: maintainer-email
Dynamic: project-url
Dynamic: requires-dist
Dynamic: summary
